{
    "cid": "23d9fd6d-f8bb-47ce-b2b3-7911a5d7a28b",
    "password": "57135971",
    "kid": 13171,
    "name": "Red-Eyes Fang with Chain",
    "name_jp": "<ruby lang=\"jp\"><rb>鎖</rb><rp> (</rp><rt>くさり</rt><rp>)</rp></ruby><ruby lang=\"jp\"><rb>付</rb><rp> (</rp><rt>つ</rt><rp>)</rp></ruby>き<ruby lang=\"jp\"><rb>真紅眼牙</rb><rp> (</rp><rt>レッドアイズファング</rt><rp>)</rp></ruby>",
    "name_jp_rom": "Kusaritsuki Reddoaizu Fangu",
    "name_jp_tl": "Chain-Attached Red-Eyes Fang",
    "type": "Trap",
    "attribute": "Trap",
    "pend": false,
    "subtypes": "Normal",
    "atk": null,
    "def": null,
    "lrl": null,
    "level": null,
    "rank": null,
    "scale": null,
    "link": null,
    "arrows": null,
    "desc": "Target 1 \"Red-Eyes\" monster you control; equip this card to it. It can make up to 2 attacks on monsters during each Battle Phase. You can send this Equip Card to the GY, then target 1 Effect Monster on the field; equip that target to the monster this card was equipped to, and if you do, while a monster is equipped to it by this effect, its ATK/DEF become equal to the original ATK/DEF of that equipped monster.",
    "pend_eff": null,
    "mnst_eff": null,
    "eff": "Target 1 \"Red-Eyes\" monster you control; equip this card to it. It can make up to 2 attacks on monsters during each Battle Phase. You can send this Equip Card to the GY, then target 1 Effect Monster on the field; equip that target to the monster this card was equipped to, and if you do, while a monster is equipped to it by this effect, its ATK/DEF become equal to the original ATK/DEF of that equipped monster.",
    "flavor": null,
    "images": {
        "1": {
            "idx": "1",
            "full": "RedEyesFangwithChain-LDS1-EN-ScR-LE.png",
            "art": null
        }
    },
    "image": null,
    "sets": [
        {
            "sid": "LEDU-EN004",
            "set": "Legendary Duelists",
            "rarities": {
                "Ultra Rare": []
            }
        },
        {
            "sid": "LDS1-EN021",
            "set": "Legendary Duelists: Season 1",
            "rarities": {
                "Secret Rare": []
            }
        }
    ],
    "misc": {
        "pend_eff_types": [],
        "eff_types": [
            "Effect, Continuous-like, Quick-like"
        ],
        "mentions": [],
        "sup": [
            "Effect Monster"
        ],
        "asup": [
            "Effect Monster"
        ],
        "arc": [
            "Red-Eyes",
            "with Chain"
        ],
        "suparc": [
            "Red-Eyes"
        ],
        "asuparc": [],
        "rel": [],
        "counter": [],
        "action": [
            "Equips self from field",
            "Sends itself from field to Graveyard for cost"
        ],
        "stat_change": [
            "Changes ATK value of equipped",
            "Changes DEF value of equipped"
        ],
        "mst": [
            "Treated as Equip Card",
            "Treats monsters as Equip Cards"
        ],
        "summoning": [],
        "attack": [
            "Allows multiple attacks on monsters"
        ],
        "banished": [],
        "life_points": [],
        "fmat": [],
        "smat": [],
        "misc": []
    }
}