{
    "cid": "5944a51a-79f4-4885-9c9a-907ed6661605",
    "yid": 61936647,
    "password": "61936647",
    "kid": 12206,
    "name": "Phantom Knights' Sword",
    "name_jp": "<ruby lang=\"jp\"><rb>幻影剣</rb><rp> (</rp><rt>ファントム・ソード</rt><rp>)</rp></ruby>",
    "name_jp_rom": "Fantomu Sōdo",
    "name_jp_rom_base": "Gen'ei Ken",
    "name_jp_tl": "Phantom Sword",
    "name_jp_tl_base": null,
    "type": "Trap",
    "attribute": "Trap",
    "pend": false,
    "subtypes": "Continuous",
    "atk": null,
    "def": null,
    "lrl": null,
    "level": null,
    "rank": null,
    "scale": null,
    "link": null,
    "arrows": null,
    "desc": "Activate this card by targeting 1 face-up monster on the field; it gains 800 ATK, also if that target would be destroyed by battle or card effect, you can destroy this card instead. When it leaves the field, destroy this card. You can banish this card from your GY, then target 1 \"The Phantom Knights\" monster in your GY; Special Summon it, but banish it when it leaves the field. You can only use this effect of \"Phantom Knights' Sword\" once per turn.",
    "pend_eff": null,
    "mnst_eff": null,
    "eff": "Activate this card by targeting 1 face-up monster on the field; it gains 800 ATK, also if that target would be destroyed by battle or card effect, you can destroy this card instead. When it leaves the field, destroy this card. You can banish this card from your GY, then target 1 \"The Phantom Knights\" monster in your GY; Special Summon it, but banish it when it leaves the field. You can only use this effect of \"Phantom Knights' Sword\" once per turn.",
    "flavor": null,
    "images": {
        "1": {
            "idx": "1",
            "full": "PhantomKnightsSword-LEHD-EN-C-1E.png",
            "art": null
        }
    },
    "image": null,
    "sets": [
        {
            "sid": "WIRA-EN010",
            "set": "Wing Raiders",
            "rarities": {
                "Rare": []
            }
        },
        {
            "sid": "LEHD-ENC22",
            "set": "Legendary Hero Decks",
            "rarities": {
                "Common": []
            }
        }
    ],
    "jp_sets": [
        {
            "sid": "SPWR-JP010",
            "set": "Booster SP: Wing Raiders",
            "rarities": {
                "Common": [],
                "Normal Parallel Rare": []
            }
        }
    ],
    "misc": {
        "pend_eff_types": [],
        "eff_types": [
            "Continuous-like, Continuous-like, Quick-like, Condition"
        ],
        "mentions": [
            "Phantom Knights' Sword"
        ],
        "sup": [],
        "asup": [],
        "arc": [
            "Phantom Knights"
        ],
        "suparc": [
            "The Phantom Knights"
        ],
        "asuparc": [],
        "rel": [],
        "counter": [],
        "action": [
            "Activates from your Graveyard"
        ],
        "stat_change": [
            "Your monsters gain ATK",
            "Your opponent's monsters gain ATK"
        ],
        "mst": [
            "Redirects destruction",
            "Cannot be destroyed by card effects",
            "Destroys itself"
        ],
        "summoning": [
            "Special Summons from your Graveyard"
        ],
        "attack": [
            "Cannot be destroyed by battle"
        ],
        "banished": [
            "Banishes itself from Graveyard for cost",
            "Banishes other cards when they leave the field"
        ],
        "life_points": [],
        "fmat": [],
        "smat": [],
        "misc": [
            "Only once per turn"
        ]
    },
    "links": {}
}