{
    "cid": "8dc65d4f-538d-4deb-98bd-4c23f2860968",
    "password": "64182380",
    "kid": 19403,
    "name": "Garunix Eternity, Hyang of the Fire Kings",
    "name_jp": "<ruby lang=\"jp\"><rb>炎</rb><rp> (</rp><rt>えん</rt><rp>)</rp></ruby><ruby lang=\"jp\"><rb>王</rb><rp> (</rp><rt>おう</rt><rp>)</rp></ruby><ruby lang=\"jp\"><rb>神</rb><rp> (</rp><rt>しん</rt><rp>)</rp></ruby> ガルドニクス・エタニティ",
    "name_jp_rom": "En'ōshin Garudonikusu Etaniti",
    "name_jp_tl": "Garudonix Eternity, God of the Flame Kings",
    "type": "Monster",
    "attribute": "FIRE",
    "pend": false,
    "subtypes": [
        "Pyro",
        "Xyz",
        "Effect"
    ],
    "atk": 3000,
    "def": 2000,
    "lrl": 8,
    "level": null,
    "rank": 8,
    "scale": null,
    "link": null,
    "arrows": null,
    "desc": "2+ Level 8 monsters<br />If this card is Xyz Summoned: You can destroy all other monsters on the field. You can detach 1 material from this card, then target 1 Spell/Trap on the field; destroy it, and if you do, this card gains 500 ATK. If this card is destroyed while it has material: You can Special Summon \"Fire King\" monsters from your GY, up to the number of materials this card had. You can only use each effect of \"Garunix Eternity, Hyang of the Fire Kings\" once per turn.",
    "pend_eff": null,
    "mnst_eff": "2+ Level 8 monsters\nIf this card is Xyz Summoned: You can destroy all other monsters on the field. You can detach 1 material from this card, then target 1 Spell/Trap on the field; destroy it, and if you do, this card gains 500 ATK. If this card is destroyed while it has material: You can Special Summon \"Fire King\" monsters from your GY, up to the number of materials this card had. You can only use each effect of \"Garunix Eternity, Hyang of the Fire Kings\" once per turn.",
    "eff": "2+ Level 8 monsters\nIf this card is Xyz Summoned: You can destroy all other monsters on the field. You can detach 1 material from this card, then target 1 Spell/Trap on the field; destroy it, and if you do, this card gains 500 ATK. If this card is destroyed while it has material: You can Special Summon \"Fire King\" monsters from your GY, up to the number of materials this card had. You can only use each effect of \"Garunix Eternity, Hyang of the Fire Kings\" once per turn.",
    "flavor": null,
    "images": {
        "1": {
            "idx": "1",
            "full": "GarunixEternityHyangoftheFireKings-25LP-EN-UR-LE.png",
            "art": null
        }
    },
    "image": null,
    "sets": [
        {
            "sid": "SR14-EN044",
            "set": "Structure Deck: Fire Kings",
            "rarities": {
                "Ultra Rare": []
            }
        },
        {
            "sid": "25LP-EN003",
            "set": "Limited Pack World Championship 2025",
            "rarities": {
                "Ultra Rare": [],
                "Secret Rare": []
            }
        }
    ],
    "misc": {
        "pend_eff_types": [],
        "eff_types": [
            "Trigger, Ignition, Trigger, Condition"
        ],
        "mentions": [],
        "sup": [],
        "asup": [],
        "arc": [
            "Fire King"
        ],
        "suparc": [
            "Fire King"
        ],
        "asuparc": [],
        "rel": [],
        "counter": [],
        "action": [
            "Activates upon Xyz Summon",
            "Activates if destroyed"
        ],
        "stat_change": [
            "This card gains ATK"
        ],
        "mst": [
            "Destroys Monster Cards",
            "Destroys Spell Cards",
            "Destroys Trap Cards"
        ],
        "summoning": [
            "2+ Xyz Materials",
            "Does not require specific Xyz Materials",
            "Special Summons from your Graveyard"
        ],
        "attack": [],
        "banished": [],
        "life_points": [],
        "fmat": [],
        "smat": [],
        "misc": [
            "Only once per turn"
        ]
    }
}