{
    "cid": "699638fe-693b-4feb-bc61-4d3c2bbb8604",
    "yid": 85446833,
    "password": "85446833",
    "kid": 10413,
    "name": "Zerozerock",
    "name_jp": "ゼロゼロック",
    "name_jp_rom": "Zerozerokku",
    "name_jp_rom_base": null,
    "name_jp_tl": null,
    "name_jp_tl_base": null,
    "type": "Spell",
    "attribute": "Spell",
    "pend": false,
    "subtypes": "Continuous",
    "atk": null,
    "def": null,
    "lrl": null,
    "level": null,
    "rank": null,
    "scale": null,
    "link": null,
    "arrows": null,
    "desc": "Your opponent cannot target face-up Attack Position monsters with 0 ATK for attacks.",
    "pend_eff": null,
    "mnst_eff": null,
    "eff": "Your opponent cannot target face-up Attack Position monsters with 0 ATK for attacks.",
    "flavor": null,
    "images": {
        "1": {
            "idx": "1",
            "full": "Zerozerock-CBLZ-EN-C-1E.png",
            "art": null
        }
    },
    "image": null,
    "sets": [
        {
            "sid": "CBLZ-EN054",
            "set": "Cosmo Blazer",
            "rarities": {
                "Common": []
            }
        }
    ],
    "jp_sets": [
        {
            "sid": "CBLZ-JP054",
            "set": "Cosmo Blazer",
            "rarities": {
                "Common": []
            }
        }
    ],
    "misc": {
        "pend_eff_types": [],
        "eff_types": [
            "Continuous-like"
        ],
        "mentions": [],
        "sup": [
            "0 ATK Monster Cards"
        ],
        "asup": [],
        "arc": [],
        "suparc": [],
        "asuparc": [],
        "rel": [],
        "counter": [],
        "action": [],
        "stat_change": [],
        "mst": [],
        "summoning": [],
        "attack": [
            "Prevents other cards being targeted for attacks"
        ],
        "banished": [],
        "life_points": [],
        "fmat": [],
        "smat": [],
        "misc": []
    },
    "links": {}
}