{
    "cid": "1c6e2ed4-603c-41e9-9f34-407fe043bd6c",
    "yid": 29876299,
    "password": "29876299",
    "kid": 21832,
    "name": "Megalith Anastasis",
    "name_jp": "メガリス・アナスタシス",
    "name_jp_rom": "Megarisu Anasutashisu",
    "name_jp_rom_base": null,
    "name_jp_tl": null,
    "name_jp_tl_base": null,
    "type": "Spell",
    "attribute": "Spell",
    "pend": false,
    "subtypes": "Continuous",
    "atk": null,
    "def": null,
    "lrl": null,
    "level": null,
    "rank": null,
    "scale": null,
    "link": null,
    "arrows": null,
    "desc": "You can discard 1 card; add 2 \"Megalith\" monsters (1 Level 4 or lower and 1 Level 8 or higher) from your Deck to your hand. You can only use this effect of \"Megalith Anastasis\" once per turn. Once per turn, if you Ritual Summon a \"Megalith\" monster (except during the Damage Step): You can activate 1 of these effects (but you can only use each of these effects of \"Megalith Anastasis\" once per turn);<br />● Draw 2 cards, then discard 1 card.<br />● Tribute 1 monster your opponent controls.",
    "pend_eff": null,
    "mnst_eff": null,
    "eff": "You can discard 1 card; add 2 \"Megalith\" monsters (1 Level 4 or lower and 1 Level 8 or higher) from your Deck to your hand. You can only use this effect of \"Megalith Anastasis\" once per turn. Once per turn, if you Ritual Summon a \"Megalith\" monster (except during the Damage Step): You can activate 1 of these effects (but you can only use each of these effects of \"Megalith Anastasis\" once per turn);\n● Draw 2 cards, then discard 1 card.\n● Tribute 1 monster your opponent controls.",
    "flavor": null,
    "images": {
        "1": {
            "idx": "1",
            "full": "MegalithAnastasis-DOOD-EN-C-1E.png",
            "art": null
        }
    },
    "image": null,
    "sets": [
        {
            "sid": "DOOD-EN066",
            "set": "Doom of Dimensions",
            "rarities": {
                "Common": []
            }
        }
    ],
    "jp_sets": [
        {
            "sid": "DOOD-JP066",
            "set": "Doom of Dimensions",
            "rarities": {
                "Common": []
            }
        }
    ],
    "misc": {
        "pend_eff_types": [],
        "eff_types": [
            "Ignition-like, Condition, Trigger-like"
        ],
        "mentions": [],
        "sup": [],
        "asup": [],
        "arc": [
            "Megalith"
        ],
        "suparc": [
            "Megalith"
        ],
        "asuparc": [],
        "rel": [],
        "counter": [],
        "action": [
            "You discard for cost",
            "Adds from Deck to hand",
            "Activates upon Ritual Summon",
            "You draw cards",
            "You discard as an effect",
            "Tributes opponent's monsters"
        ],
        "stat_change": [],
        "mst": [],
        "summoning": [],
        "attack": [],
        "banished": [],
        "life_points": [],
        "fmat": [],
        "smat": [],
        "misc": [
            "Only once per turn",
            "Limited activations",
            "Requires control of specific Monster card type",
            "Requires control of specific archetype",
            "Variable effects"
        ]
    },
    "links": {}
}