{
    "cid": "6f99fc7c-5a1a-42be-ab91-25881c3df0de",
    "yid": 6589707,
    "password": "06589707",
    "kid": 17824,
    "name": "Terrors in the Hidden City",
    "name_jp": "<ruby lang=\"jp\"><rb>地</rb><rp> (</rp><rt>ち</rt><rp>)</rp></ruby><ruby lang=\"jp\"><rb>中</rb><rp> (</rp><rt>ちゅう</rt><rp>)</rp></ruby><ruby lang=\"jp\"><rb>界</rb><rp> (</rp><rt>かい</rt><rp>)</rp></ruby>の<ruby lang=\"jp\"><rb>厄</rb><rp> (</rp><rt>やく</rt><rp>)</rp></ruby><ruby lang=\"jp\"><rb>災</rb><rp> (</rp><rt>さい</rt><rp>)</rp></ruby>",
    "name_jp_rom": "Chichūkai no Yakusai",
    "name_jp_tl": "Calamity in the Mediterranean World",
    "type": "Spell",
    "attribute": "Spell",
    "pend": false,
    "subtypes": "Continuous",
    "atk": null,
    "def": null,
    "lrl": null,
    "level": null,
    "rank": null,
    "scale": null,
    "link": null,
    "arrows": null,
    "desc": "Your opponent cannot target face-down Defense Position monsters you control with card effects. Monsters you control that were flipped face-up while this card was face-up on the field gain 1500 ATK/DEF. If this card in its owner's Spell & Trap Zone is destroyed by an opponent's card effect: You can target 1 monster in your GY; Special Summon it in face-down Defense Position.",
    "pend_eff": null,
    "mnst_eff": null,
    "eff": "Your opponent cannot target face-down Defense Position monsters you control with card effects. Monsters you control that were flipped face-up while this card was face-up on the field gain 1500 ATK/DEF. If this card in its owner's Spell & Trap Zone is destroyed by an opponent's card effect: You can target 1 monster in your GY; Special Summon it in face-down Defense Position.",
    "flavor": null,
    "images": {
        "1": {
            "idx": "1",
            "full": "TerrorsintheHiddenCity-PHRE-EN-R-1E.png",
            "art": null
        }
    },
    "image": null,
    "sets": [
        {
            "sid": "DABL-EN069",
            "set": "Darkwing Blast",
            "rarities": {
                "Super Rare": []
            }
        },
        {
            "sid": "MP23-EN206",
            "set": "25th Anniversary Tin: Dueling Heroes Mega Pack",
            "rarities": {
                "Common": []
            }
        },
        {
            "sid": "PHRE-EN054",
            "set": "Phantom Revenge",
            "rarities": {
                "Rare": [],
                "Super Rare": []
            }
        }
    ],
    "misc": {
        "pend_eff_types": [],
        "eff_types": [
            "Continuous-like, Continuous-like, Trigger-like"
        ],
        "mentions": [],
        "sup": [],
        "asup": [],
        "arc": [],
        "suparc": [],
        "asuparc": [],
        "rel": [
            "Subterror"
        ],
        "counter": [],
        "action": [
            "Activates if destroyed by card effect"
        ],
        "stat_change": [
            "Your monsters gain ATK",
            "Your monsters gain DEF"
        ],
        "mst": [
            "Prevents other cards being targeted by card effects"
        ],
        "summoning": [
            "Special Summons from your Graveyard",
            "Special Summons face-down"
        ],
        "attack": [],
        "banished": [],
        "life_points": [],
        "fmat": [],
        "smat": [],
        "misc": []
    },
    "links": {}
}