{
    "cid": "d7a87e38-49d6-4d38-ad7a-5f42e5b7a245",
    "yid": 13382806,
    "password": "13382806",
    "kid": 16836,
    "name": "Silvervine Senri",
    "name_jp": "マタタビ<ruby lang=\"jp\"><rb>仙</rb><rp> (</rp><rt>せん</rt><rp>)</rp></ruby><ruby lang=\"jp\"><rb>狸</rb><rp> (</rp><rt>り</rt><rp>)</rp></ruby>",
    "name_jp_rom": "Matatabi Senri",
    "name_jp_rom_base": null,
    "name_jp_tl": null,
    "name_jp_tl_base": null,
    "type": "Monster",
    "attribute": "WIND",
    "pend": false,
    "subtypes": [
        "Beast",
        "Effect"
    ],
    "atk": 0,
    "def": 0,
    "lrl": 2,
    "level": 2,
    "rank": null,
    "scale": null,
    "link": null,
    "arrows": null,
    "desc": "You can Tribute this card, then target 1 Level 2 monster in your GY, except \"Silvervine Senri\"; Special Summon it, then you can Special Summon 1 Level 2 monster from your hand with a different Attribute than the monster Special Summoned by this effect. You can only use this effect of \"Silvervine Senri\" once per turn.",
    "pend_eff": null,
    "mnst_eff": "You can Tribute this card, then target 1 Level 2 monster in your GY, except \"Silvervine Senri\"; Special Summon it, then you can Special Summon 1 Level 2 monster from your hand with a different Attribute than the monster Special Summoned by this effect. You can only use this effect of \"Silvervine Senri\" once per turn.",
    "eff": "You can Tribute this card, then target 1 Level 2 monster in your GY, except \"Silvervine Senri\"; Special Summon it, then you can Special Summon 1 Level 2 monster from your hand with a different Attribute than the monster Special Summoned by this effect. You can only use this effect of \"Silvervine Senri\" once per turn.",
    "flavor": null,
    "images": {
        "1": {
            "idx": "1",
            "full": "SilvervineSenri-BACH-EN-C-1E.png",
            "art": null
        }
    },
    "image": null,
    "sets": [
        {
            "sid": "BACH-EN031",
            "set": "Battle of Chaos",
            "rarities": {
                "Common": []
            }
        }
    ],
    "jp_sets": [
        {
            "sid": "BACH-JP031",
            "set": "Battle of Chaos",
            "rarities": {
                "Common": []
            }
        }
    ],
    "misc": {
        "pend_eff_types": [],
        "eff_types": [
            "Ignition, Condition"
        ],
        "mentions": [
            "Silvervine Senri"
        ],
        "sup": [],
        "asup": [],
        "arc": [],
        "suparc": [],
        "asuparc": [],
        "rel": [],
        "counter": [],
        "action": [
            "Tributes itself for cost"
        ],
        "stat_change": [],
        "mst": [],
        "summoning": [
            "Special Summons from your Graveyard",
            "Special Summons from your hand"
        ],
        "attack": [],
        "banished": [],
        "life_points": [],
        "fmat": [],
        "smat": [],
        "misc": [
            "Only once per turn"
        ]
    },
    "links": {}
}