{
    "cid": "96b57752-9a0e-4816-91fe-4b66437dacb4",
    "yid": 8955148,
    "password": "08955148",
    "kid": 13812,
    "name": "Litmus Doom Ritual",
    "name_jp": "リトマスの<ruby lang=\"jp\"><rb>死</rb><rp> (</rp><rt>し</rt><rp>)</rp></ruby><ruby lang=\"jp\"><rb>儀</rb><rp> (</rp><rt>ぎ</rt><rp>)</rp></ruby><ruby lang=\"jp\"><rb>式</rb><rp> (</rp><rt>しき</rt><rp>)</rp></ruby>",
    "name_jp_rom": "Ritomasu no Shigishiki",
    "name_jp_rom_base": null,
    "name_jp_tl": "Litmus Death Ritual",
    "name_jp_tl_base": null,
    "type": "Spell",
    "attribute": "Spell",
    "pend": false,
    "subtypes": "Ritual",
    "atk": null,
    "def": null,
    "lrl": null,
    "level": null,
    "rank": null,
    "scale": null,
    "link": null,
    "arrows": null,
    "desc": "This card is used to Ritual Summon \"Litmus Doom Swordsman\". You must also Tribute monsters from your hand or field, whose total Levels equal 8 or more. If this card is in the GY: You can target 1 \"Litmus Doom Swordsman\" in your GY; shuffle both it and this card from the GY into the Deck, then draw 1 card. You can only use this effect of \"Litmus Doom Ritual\" once per turn.",
    "pend_eff": null,
    "mnst_eff": null,
    "eff": "This card is used to Ritual Summon \"Litmus Doom Swordsman\". You must also Tribute monsters from your hand or field, whose total Levels equal 8 or more. If this card is in the GY: You can target 1 \"Litmus Doom Swordsman\" in your GY; shuffle both it and this card from the GY into the Deck, then draw 1 card. You can only use this effect of \"Litmus Doom Ritual\" once per turn.",
    "flavor": null,
    "images": {
        "1": {
            "idx": "1",
            "full": "LitmusDoomRitual-BLRR-EN-UR-1E.png",
            "art": null
        }
    },
    "image": null,
    "sets": [
        {
            "sid": "BLRR-EN014",
            "set": "Battles of Legend: Relentless Revenge",
            "rarities": {
                "Ultra Rare": []
            }
        }
    ],
    "jp_sets": [
        {
            "sid": "CP18-JP014",
            "set": "Collectors Pack 2018",
            "rarities": {
                "Common": []
            }
        }
    ],
    "misc": {
        "pend_eff_types": [],
        "eff_types": [
            "Effect, Ignition-like, Condition"
        ],
        "mentions": [
            "Litmus Doom Swordsman"
        ],
        "sup": [],
        "asup": [],
        "arc": [],
        "suparc": [],
        "asuparc": [],
        "rel": [],
        "counter": [],
        "action": [
            "Tributes as an effect",
            "Activates from your Graveyard",
            "Returns itself from Graveyard to Deck",
            "Returns from your Graveyard to your Deck",
            "You draw cards"
        ],
        "stat_change": [],
        "mst": [],
        "summoning": [
            "Special Summons from your hand"
        ],
        "attack": [],
        "banished": [],
        "life_points": [],
        "fmat": [],
        "smat": [],
        "misc": [
            "Only once per turn",
            "Specific Ritual Spell Card"
        ]
    },
    "links": {}
}