{
    "cid": "baa03bda-951f-49eb-b1eb-98a0cb5f0bda",
    "yid": null,
    "password": "20455229",
    "kid": 18464,
    "name": "Firewall Defenser",
    "name_jp": "ファイアウォール・ディフェンサー",
    "name_jp_rom": "Faiawōru Difensā",
    "name_jp_tl": null,
    "type": "Monster",
    "attribute": "DARK",
    "pend": false,
    "subtypes": [
        "Cyberse",
        "Effect"
    ],
    "atk": 1200,
    "def": 1500,
    "lrl": 4,
    "level": 4,
    "rank": null,
    "scale": null,
    "link": null,
    "arrows": null,
    "desc": "If this card is sent to the GY as material for the Link Summon of a Cyberse monster: You can Special Summon 1 \"Firewall\" monster from your Deck, except \"Firewall Defenser\". You cannot Special Summon monsters the turn you activate this effect, except Cyberse monsters. If a \"Firewall\" monster(s) you control would be destroyed by card effect, you can banish this card from your GY instead. You can only use each effect of \"Firewall Defenser\" once per turn.",
    "pend_eff": null,
    "mnst_eff": "If this card is sent to the GY as material for the Link Summon of a Cyberse monster: You can Special Summon 1 \"Firewall\" monster from your Deck, except \"Firewall Defenser\". You cannot Special Summon monsters the turn you activate this effect, except Cyberse monsters. If a \"Firewall\" monster(s) you control would be destroyed by card effect, you can banish this card from your GY instead. You can only use each effect of \"Firewall Defenser\" once per turn.",
    "eff": "If this card is sent to the GY as material for the Link Summon of a Cyberse monster: You can Special Summon 1 \"Firewall\" monster from your Deck, except \"Firewall Defenser\". You cannot Special Summon monsters the turn you activate this effect, except Cyberse monsters. If a \"Firewall\" monster(s) you control would be destroyed by card effect, you can banish this card from your GY instead. You can only use each effect of \"Firewall Defenser\" once per turn.",
    "flavor": null,
    "images": {
        "1": {
            "idx": "1",
            "full": "FirewallDefenser-CYAC-EN-UR-1E.png",
            "art": null
        }
    },
    "image": null,
    "sets": [
        {
            "sid": "CYAC-EN001",
            "set": "Cyberstorm Access",
            "rarities": {
                "Ultra Rare": []
            }
        }
    ],
    "misc": {
        "pend_eff_types": [],
        "eff_types": [
            "Trigger, Condition, Unclassified, Condition"
        ],
        "mentions": [
            "Firewall Defenser"
        ],
        "sup": [
            "Cyberse",
            "Link Monster"
        ],
        "asup": [],
        "arc": [
            "Firewall (archetype)"
        ],
        "suparc": [
            "Firewall (archetype)"
        ],
        "asuparc": [],
        "rel": [],
        "counter": [],
        "action": [
            "Activates from your Graveyard",
            "Activates if used as Link Material"
        ],
        "stat_change": [],
        "mst": [
            "Prevents other cards being destroyed by card effects",
            "Redirects destruction"
        ],
        "summoning": [
            "Special Summons from your Deck",
            "Restricts the player's Special Summons to Type specific monsters"
        ],
        "attack": [],
        "banished": [
            "Banishes itself from Graveyard"
        ],
        "life_points": [],
        "fmat": [],
        "smat": [],
        "misc": [
            "Requires control of specific archetype",
            "Only once per turn"
        ]
    }
}