{
    "cid": "1ece6ccc-aaa4-4f56-b25c-7d7c512e0f51",
    "yid": 14812471,
    "password": "14812471",
    "kid": 14249,
    "name": "Salamangreat Balelynx",
    "name_jp": "<ruby lang=\"jp\"><rb>転生炎獣</rb><rp> (</rp><rt>サラマングレイト</rt><rp>)</rp></ruby>ベイルリンクス",
    "name_jp_rom": "Saramangureito Beiru Rinkusu",
    "name_jp_rom_base": null,
    "name_jp_tl": null,
    "name_jp_tl_base": null,
    "type": "Monster",
    "attribute": "FIRE",
    "pend": false,
    "subtypes": [
        "Cyberse",
        "Link",
        "Effect"
    ],
    "atk": 500,
    "def": null,
    "lrl": 1,
    "level": null,
    "rank": null,
    "scale": null,
    "link": 1,
    "arrows": [
        "Bottom-Center"
    ],
    "desc": "1 Level 4 or lower Cyberse monster<br />If this card is Link Summoned: You can add 1 \"Salamangreat Sanctuary\" from your Deck to your hand. If a \"Salamangreat\" card(s) you control would be destroyed by battle or card effect, you can banish this card from your GY instead. You can only use each effect of \"Salamangreat Balelynx\" once per turn.",
    "pend_eff": null,
    "mnst_eff": "1 Level 4 or lower Cyberse monster\nIf this card is Link Summoned: You can add 1 \"Salamangreat Sanctuary\" from your Deck to your hand. If a \"Salamangreat\" card(s) you control would be destroyed by battle or card effect, you can banish this card from your GY instead. You can only use each effect of \"Salamangreat Balelynx\" once per turn.",
    "eff": "1 Level 4 or lower Cyberse monster\nIf this card is Link Summoned: You can add 1 \"Salamangreat Sanctuary\" from your Deck to your hand. If a \"Salamangreat\" card(s) you control would be destroyed by battle or card effect, you can banish this card from your GY instead. You can only use each effect of \"Salamangreat Balelynx\" once per turn.",
    "flavor": null,
    "images": {
        "1": {
            "idx": "1",
            "full": "SalamangreatBalelynx-LD10-EN-R-1E.png",
            "art": null
        }
    },
    "image": null,
    "sets": [
        {
            "sid": "SDSB-EN043",
            "set": "Structure Deck: Soulburner",
            "rarities": {
                "Ultra Rare": []
            }
        },
        {
            "sid": "LD10-EN012",
            "set": "Legendary Duelists: Soulburning Volcano",
            "rarities": {
                "Rare": []
            }
        }
    ],
    "jp_sets": [
        {
            "sid": "SD35-JPP02",
            "set": "Structure Deck: Soulburner Extra Deck Enhancement Pack",
            "rarities": {
                "Ultra Rare": [],
                "Secret Rare": []
            }
        },
        {
            "sid": "DP28-JP011",
            "set": "Duelist Pack: Duelists of Explosion",
            "rarities": {
                "Common": []
            }
        }
    ],
    "misc": {
        "pend_eff_types": [],
        "eff_types": [
            "Trigger, Unclassified, Condition"
        ],
        "mentions": [
            "Salamangreat Sanctuary"
        ],
        "sup": [
            "Cyberse"
        ],
        "asup": [],
        "arc": [
            "Field Searcher",
            "Salamangreat"
        ],
        "suparc": [
            "Salamangreat"
        ],
        "asuparc": [],
        "rel": [],
        "counter": [],
        "action": [
            "Activates upon Link Summon",
            "Adds from Deck to hand",
            "Activates from your Graveyard"
        ],
        "stat_change": [],
        "mst": [
            "Redirects destruction",
            "Cannot be destroyed by card effects"
        ],
        "summoning": [
            "1 Link Material",
            "Requires Level specific Link Materials",
            "Requires Type specific Link Materials"
        ],
        "attack": [
            "Cannot be destroyed by battle"
        ],
        "banished": [
            "Banishes itself from Graveyard"
        ],
        "life_points": [],
        "fmat": [],
        "smat": [],
        "misc": [
            "Only once per turn"
        ]
    },
    "links": {}
}