{
    "cid": "7cdddb38-fd5c-41b6-bd9b-ba1e4714f118",
    "password": "62966332",
    "kid": 5392,
    "name": "Convulsion of Nature",
    "name_jp": "<ruby lang=\"jp\"><rb>天</rb><rp> (</rp><rt>てん</rt><rp>)</rp></ruby><ruby lang=\"jp\"><rb>変</rb><rp> (</rp><rt>ぺん</rt><rp>)</rp></ruby><ruby lang=\"jp\"><rb>地</rb><rp> (</rp><rt>ち</rt><rp>)</rp></ruby><ruby lang=\"jp\"><rb>異</rb><rp> (</rp><rt>い</rt><rp>)</rp></ruby>",
    "name_jp_rom": "Tenpenchii",
    "name_jp_tl": "Cataclysm",
    "type": "Spell",
    "attribute": "Spell",
    "pend": false,
    "subtypes": "Continuous",
    "atk": null,
    "def": null,
    "lrl": null,
    "level": null,
    "rank": null,
    "scale": null,
    "link": null,
    "arrows": null,
    "desc": "As long as this card remains face-up on the field, both players must turn their respective Decks upside down and proceed with the current Duel.",
    "pend_eff": null,
    "mnst_eff": null,
    "eff": "As long as this card remains face-up on the field, both players must turn their respective Decks upside down and proceed with the current Duel.",
    "flavor": null,
    "images": {
        "1": {
            "idx": "1",
            "full": "ConvulsionofNature-DB2-EN-C-UE.png",
            "art": null
        }
    },
    "image": null,
    "sets": [
        {
            "sid": "LOD-EN084",
            "set": "Legacy of Darkness",
            "rarities": {
                "Common": []
            }
        },
        {
            "sid": "DB2-EN193",
            "set": "Dark Beginning 2",
            "rarities": {
                "Common": []
            }
        }
    ],
    "misc": {
        "pend_eff_types": [],
        "eff_types": [
            "Continuous-like"
        ],
        "mentions": [],
        "sup": [],
        "asup": [],
        "arc": [],
        "suparc": [],
        "asuparc": [],
        "rel": [],
        "counter": [],
        "action": [
            "Allows face-up cards in Main Deck"
        ],
        "stat_change": [],
        "mst": [],
        "summoning": [],
        "attack": [],
        "banished": [],
        "life_points": [],
        "fmat": [],
        "smat": [],
        "misc": []
    }
}