{
    "cid": "54b18672-7e85-41df-af10-1df8d52a6c5b",
    "password": "94463200",
    "kid": 5794,
    "name": "Battle-Scarred",
    "name_jp": "<ruby lang=\"jp\"><rb>血</rb><rp> (</rp><rt>ち</rt><rp>)</rp></ruby>の<ruby lang=\"jp\"><rb>刻</rb><rp> (</rp><rt>こく</rt><rp>)</rp></ruby><ruby lang=\"jp\"><rb>印</rb><rp> (</rp><rt>いん</rt><rp>)</rp></ruby>",
    "name_jp_rom": "Chi no Kokuin",
    "name_jp_tl": "Mark of Blood",
    "type": "Trap",
    "attribute": "Trap",
    "pend": false,
    "subtypes": "Continuous",
    "atk": null,
    "def": null,
    "lrl": null,
    "level": null,
    "rank": null,
    "scale": null,
    "link": null,
    "arrows": null,
    "desc": "Activate this card by targeting 1 \"Archfiend\" monster you control. Your opponent also pays the same LP that you pay for that monster during the Standby Phase. When this card leaves the field, destroy that monster. If that monster leaves the field, destroy this card.",
    "pend_eff": null,
    "mnst_eff": null,
    "eff": "Activate this card by targeting 1 \"Archfiend\" monster you control. Your opponent also pays the same LP that you pay for that monster during the Standby Phase. When this card leaves the field, destroy that monster. If that monster leaves the field, destroy this card.",
    "flavor": null,
    "images": {
        "1": {
            "idx": "1",
            "full": "BattleScarred-EE1-JP-C.jpg",
            "art": "BattleScarred-MADU-JP-VG-artwork.png"
        },
        "1.1": {
            "idx": "1.1",
            "full": "BattleScarred-DCR-EN-C-UE-25thAnniversaryEdition.png",
            "art": "BattleScarred-MADU-EN-VG-artwork.png"
        }
    },
    "image": "1.1",
    "sets": [
        {
            "sid": "DR1-EN259",
            "set": "Dark Revelation Volume 1",
            "rarities": {
                "Common": []
            }
        },
        {
            "sid": "DCR-EN097",
            "set": "Dark Crisis",
            "rarities": {
                "Common": []
            }
        },
        {
            "sid": "SGX3-ENE19",
            "set": "Speed Duel GX: Duelists of Shadows",
            "rarities": {
                "Common": []
            }
        },
        {
            "sid": "DCR-EN097",
            "set": "Dark Crisis (25th Anniversary Edition)",
            "rarities": {
                "Common": []
            }
        }
    ],
    "misc": {
        "pend_eff_types": [],
        "eff_types": [
            "Continuous-like, Continuous-like, Continuous-like"
        ],
        "mentions": [],
        "sup": [],
        "asup": [],
        "arc": [],
        "suparc": [
            "Archfiend"
        ],
        "asuparc": [],
        "rel": [],
        "counter": [],
        "action": [],
        "stat_change": [],
        "mst": [
            "Destroys your Monster Cards",
            "Destroys itself"
        ],
        "summoning": [],
        "attack": [],
        "banished": [],
        "life_points": [
            "Your opponent pays Life Points for cost"
        ],
        "fmat": [],
        "smat": [],
        "misc": [
            "During the Standby Phase"
        ]
    }
}