{
    "cid": "4d9b4736-6b50-4fbc-99d6-d15f8dcb882a",
    "yid": 94770493,
    "password": "94770493",
    "kid": 9663,
    "name": "Double or Nothing!",
    "name_jp": "ダブル・アップ・チャンス",
    "name_jp_rom": "Daburu Appu Chansu",
    "name_jp_rom_base": null,
    "name_jp_tl": "Double Up Chance",
    "name_jp_tl_base": null,
    "type": "Spell",
    "attribute": "Spell",
    "pend": false,
    "subtypes": "Quick-Play",
    "atk": null,
    "def": null,
    "lrl": null,
    "level": null,
    "rank": null,
    "scale": null,
    "link": null,
    "arrows": null,
    "desc": "When a monster's attack is negated: Target that monster; it can make a second attack during this Battle Phase, and if it does, its ATK is doubled during the Damage Step only.",
    "pend_eff": null,
    "mnst_eff": null,
    "eff": "When a monster's attack is negated: Target that monster; it can make a second attack during this Battle Phase, and if it does, its ATK is doubled during the Damage Step only.",
    "flavor": null,
    "images": {
        "1": {
            "idx": "1",
            "full": "DoubleorNothing-RA04-EN-PlScR-1E.png",
            "art": null
        }
    },
    "image": null,
    "sets": [
        {
            "sid": "GENF-EN046",
            "set": "Generation Force",
            "rarities": {
                "Common": []
            }
        },
        {
            "sid": "YS13-EN024",
            "set": "Super Starter: V for Victory",
            "rarities": {
                "Common": []
            }
        },
        {
            "sid": "DUPO-EN064",
            "set": "Duel Power",
            "rarities": {
                "Ultra Rare": []
            }
        },
        {
            "sid": "RA04-EN156",
            "set": "Quarter Century Stampede",
            "rarities": {
                "Platinum Secret Rare": [],
                "Quarter Century Secret Rare": []
            }
        }
    ],
    "jp_sets": [
        {
            "sid": "GENF-JP046",
            "set": "Generation Force",
            "rarities": {
                "Common": []
            }
        },
        {
            "sid": "DP12-JP019",
            "set": "Duelist Pack: Yuma",
            "rarities": {
                "Rare": []
            }
        },
        {
            "sid": "ST13-JP024",
            "set": "Starter Deck 2013",
            "rarities": {
                "Common": []
            }
        },
        {
            "sid": "20TH-JPB23",
            "set": "20th Anniversary Duelist Box",
            "rarities": {
                "Normal Parallel Rare": []
            }
        },
        {
            "sid": "SD42-JP030",
            "set": "Structure Deck: Overlay Universe",
            "rarities": {
                "Common": []
            }
        },
        {
            "sid": "QCCU-JP070",
            "set": "Quarter Century Chronicle side:Unity",
            "rarities": {
                "Ultra Rare": [],
                "Secret Rare": [],
                "Quarter Century Secret Rare": []
            }
        }
    ],
    "misc": {
        "pend_eff_types": [],
        "eff_types": [
            "Activation requirement, Effect"
        ],
        "mentions": [],
        "sup": [],
        "asup": [],
        "arc": [],
        "suparc": [],
        "asuparc": [],
        "rel": [
            "Number",
            "Utopia (archetype)",
            "Utopic"
        ],
        "counter": [],
        "action": [],
        "stat_change": [
            "Your monsters gain ATK",
            "Your opponent's monsters gain ATK",
            "Doubles ATK"
        ],
        "mst": [],
        "summoning": [],
        "attack": [
            "Allows multiple attacks"
        ],
        "banished": [],
        "life_points": [],
        "fmat": [],
        "smat": [],
        "misc": []
    },
    "links": {}
}