{
    "cid": "ed9a1c38-57be-406a-a0cc-eff34b918b5b",
    "password": "71734607",
    "kid": 15110,
    "name": "Rikka Petal",
    "name_jp": "<ruby lang=\"jp\"><rb>六</rb><rp> (</rp><rt>りっ</rt><rp>)</rp></ruby><ruby lang=\"jp\"><rb>花</rb><rp> (</rp><rt>か</rt><rp>)</rp></ruby>のひとひら",
    "name_jp_rom": "Rikka no Hitohira",
    "name_jp_tl": "Snowflower Petal",
    "type": "Monster",
    "attribute": "WATER",
    "pend": false,
    "subtypes": [
        "Plant",
        "Effect"
    ],
    "atk": 0,
    "def": 0,
    "lrl": 1,
    "level": 1,
    "rank": null,
    "scale": null,
    "link": null,
    "arrows": null,
    "desc": "During your Main Phase: You can take 1 \"Rikka\" monster from your Deck, except \"Rikka Petal\", and either add it to your hand or send it to the GY, also you cannot Special Summon for the rest of this turn, except Plant monsters. During your opponent's End Phase, while this card is in your GY, if you control no monsters or all monsters you control are Plant monsters: You can Special Summon this card. You can only use each effect of \"Rikka Petal\" once per turn.",
    "pend_eff": null,
    "mnst_eff": "During your Main Phase: You can take 1 \"Rikka\" monster from your Deck, except \"Rikka Petal\", and either add it to your hand or send it to the GY, also you cannot Special Summon for the rest of this turn, except Plant monsters. During your opponent's End Phase, while this card is in your GY, if you control no monsters or all monsters you control are Plant monsters: You can Special Summon this card. You can only use each effect of \"Rikka Petal\" once per turn.",
    "eff": "During your Main Phase: You can take 1 \"Rikka\" monster from your Deck, except \"Rikka Petal\", and either add it to your hand or send it to the GY, also you cannot Special Summon for the rest of this turn, except Plant monsters. During your opponent's End Phase, while this card is in your GY, if you control no monsters or all monsters you control are Plant monsters: You can Special Summon this card. You can only use each effect of \"Rikka Petal\" once per turn.",
    "flavor": null,
    "images": {
        "1": {
            "idx": "1",
            "full": "RikkaPetal-MAZE-EN-R-1E.png",
            "art": null
        }
    },
    "image": null,
    "sets": [
        {
            "sid": "SESL-EN014",
            "set": "Secret Slayers",
            "rarities": {
                "Super Rare": []
            }
        },
        {
            "sid": "MAZE-EN047",
            "set": "Maze of Memories",
            "rarities": {
                "Rare": []
            }
        }
    ],
    "misc": {
        "pend_eff_types": [],
        "eff_types": [
            "Ignition, Trigger, Condition"
        ],
        "mentions": [
            "Rikka Petal"
        ],
        "sup": [
            "Plant"
        ],
        "asup": [],
        "arc": [
            "Rikka"
        ],
        "suparc": [
            "Rikka"
        ],
        "asuparc": [],
        "rel": [],
        "counter": [],
        "action": [
            "Adds from Deck to hand",
            "Sends from your Deck to your Graveyard",
            "Activates from your Graveyard"
        ],
        "stat_change": [],
        "mst": [],
        "summoning": [
            "Restricts the player's Special Summons to Type specific monsters",
            "Special Summons itself from your Graveyard"
        ],
        "attack": [],
        "banished": [],
        "life_points": [],
        "fmat": [],
        "smat": [],
        "misc": [
            "Requires control of no monsters",
            "Requires control of specific Type",
            "Only once per turn"
        ]
    }
}